geocat/viz/__init__.py
geocat/viz/taylor.py
geocat/viz/util.py
geocat_viz-2025.7.0.dist-info/licenses/LICENSE
geocat_viz-2025.7.0.dist-info/METADATA
geocat_viz-2025.7.0.dist-info/WHEEL
geocat_viz-2025.7.0.dist-info/top_level.txt
geocat_viz-2025.7.0.dist-info/RECORD
