Metadata-Version: 2.4
Name: geocat.viz
Version: 2025.7.0
Summary: GeoCAT-viz is the visualization component of the GeoCAT project and provides implementations of convenience functions for publication-ready plotting of geosciences data
Author-email: GeoCAT Team <geocat@ucar.edu>
License-Expression: Apache-2.0
Project-URL: documentation, https://geocat-viz.readthedocs.io
Project-URL: issue-tracker, https://github.com/NCAR/geocat-viz/issues
Project-URL: source-code, https://github.com/NCAR/geocat-viz
Classifier: Operating System :: OS Independent
Classifier: Intended Audience :: Science/Research
Classifier: Programming Language :: Python
Classifier: Programming Language :: Python :: 3
Classifier: Programming Language :: Python :: 3.10
Classifier: Programming Language :: Python :: 3.11
Classifier: Programming Language :: Python :: 3.12
Classifier: Programming Language :: Python :: 3.13
Classifier: Topic :: Scientific/Engineering
Requires-Python: >=3.10
License-File: LICENSE
Requires-Dist: packaging
Requires-Dist: matplotlib
Requires-Dist: xarray
Requires-Dist: numpy
Requires-Dist: cartopy
Requires-Dist: cmaps
Requires-Dist: metpy
Requires-Dist: pint
Requires-Dist: scikit-learn
Dynamic: license-file
